README.md
setup.py
pbr_distributions/Binomialdistribution.py
pbr_distributions/Gaussiandistribution.py
pbr_distributions/Generaldistribution.py
pbr_distributions/__init__.py
pbr_distributions.egg-info/PKG-INFO
pbr_distributions.egg-info/SOURCES.txt
pbr_distributions.egg-info/dependency_links.txt
pbr_distributions.egg-info/not-zip-safe
pbr_distributions.egg-info/top_level.txt